chuk_protocol_server/__init__.py
chuk_protocol_server/cli.py
chuk_protocol_server/echo_launcher.py
chuk_protocol_server/guess_who_launcher.py
chuk_protocol_server/sample_server_launcher.py
chuk_protocol_server/server_config.py
chuk_protocol_server/server_launcher.py
chuk_protocol_server/handlers/__init__.py
chuk_protocol_server/handlers/base_handler.py
chuk_protocol_server/handlers/character_handler.py
chuk_protocol_server/handlers/connection_handler.py
chuk_protocol_server/handlers/line_handler.py
chuk_protocol_server/handlers/telnet_handler.py
chuk_protocol_server/protocols/__init__.py
chuk_protocol_server/protocols/telnet/__init__.py
chuk_protocol_server/protocols/telnet/constants.py
chuk_protocol_server/protocols/telnet/negotiation.py
chuk_protocol_server/protocols/telnet/options.py
chuk_protocol_server/protocols/telnet/terminal.py
chuk_protocol_server/sample_servers/__init__.py
chuk_protocol_server/sample_servers/__pycache__/__init__.cpython-311.pyc
chuk_protocol_server/sample_servers/echo_server/__init__.py
chuk_protocol_server/sample_servers/echo_server/config.yaml
chuk_protocol_server/sample_servers/echo_server/server.py
chuk_protocol_server/sample_servers/echo_server/__pycache__/__init__.cpython-311.pyc
chuk_protocol_server/sample_servers/echo_server/__pycache__/server.cpython-311.pyc
chuk_protocol_server/sample_servers/guess_who_server/__init__.py
chuk_protocol_server/sample_servers/guess_who_server/config.yaml
chuk_protocol_server/sample_servers/guess_who_server/server.py
chuk_protocol_server/sample_servers/guess_who_server/__pycache__/__init__.cpython-311.pyc
chuk_protocol_server/sample_servers/guess_who_server/__pycache__/server.cpython-311.pyc
chuk_protocol_server/servers/__init__.py
chuk_protocol_server/servers/base_server.py
chuk_protocol_server/servers/base_ws_server.py
chuk_protocol_server/servers/tcp_server.py
chuk_protocol_server/servers/telnet_server.py
chuk_protocol_server/servers/ws_server_plain.py
chuk_protocol_server-0.2.dist-info/METADATA
chuk_protocol_server-0.2.dist-info/WHEEL
chuk_protocol_server-0.2.dist-info/entry_points.txt
chuk_protocol_server-0.2.dist-info/top_level.txt
chuk_protocol_server-0.2.dist-info/RECORD
