Metadata-Version: 2.4
Name: chuk-protocol-server
Version: 0.2
Summary: A production ready protocol library for tcp, websocket and telnet servers
Author-email: Chris Hay <your.email@example.com>
License: MIT
Project-URL: Homepage, https://github.com/chrishayuk/chuk-protocol-server
Project-URL: Bug Tracker, https://github.com/chrishayuk/chuk-protocol-server/issues
Project-URL: Documentation, https://github.com/chrishayuk/chuk-protocol-server#readme
Keywords: tcp,telnet,websockets
Requires-Python: >=3.11
Requires-Dist: asyncio>=3.4.3
Requires-Dist: pyyaml>=6.0.2
Requires-Dist: websockets>=15.0.1
